{
  "$schema": "https://developer.microsoft.com/json-schemas/fabric/item/report/definition/visualContainer/2.6.0/schema.json",
  "name": "8a3d2e28680e0eeaeac1",
  "position": {
    "x": 469.73239436619781,
    "y": 0,
    "z": 3000,
    "height": 431.54929577464793,
    "width": 197.18309859154931,
    "tabOrder": 3000
  },
  "visual": {
    "visualType": "tableEx",
    "query": {
      "queryState": {
        "Values": {
          "projections": [
            {
              "field": {
                "Column": {
                  "Expression": {
                    "SourceRef": {
                      "Entity": "DimCalendario"
                    }
                  },
                  "Property": "AñoMes"
                }
              },
              "queryRef": "DimCalendario.AñoMes",
              "nativeQueryRef": "AñoMes"
            },
            {
              "field": {
                "Column": {
                  "Expression": {
                    "SourceRef": {
                      "Entity": "DimCalendario"
                    }
                  },
                  "Property": "Dia"
                }
              },
              "queryRef": "Sum(DimCalendario.Dia)",
              "nativeQueryRef": "Dia"
            },
            {
              "field": {
                "Aggregation": {
                  "Expression": {
                    "Column": {
                      "Expression": {
                        "SourceRef": {
                          "Entity": "main"
                        }
                      },
                      "Property": "input_majo.Responsabilidad"
                    }
                  },
                  "Function": 5
                }
              },
              "queryRef": "main.input_majo.Responsabilidad",
              "nativeQueryRef": "Base de datos",
              "displayName": "Base de datos"
            }
          ]
        }
      }
    },
    "drillFilterOtherVisuals": true
  },
  "filterConfig": {
    "filters": [
      {
        "name": "fdfc21ef28a67ad2296c",
        "ordinal": 0,
        "field": {
          "Column": {
            "Expression": {
              "SourceRef": {
                "Entity": "DimCalendario"
              }
            },
            "Property": "AñoMes"
          }
        },
        "type": "Categorical"
      },
      {
        "name": "70b484846d16da040c07",
        "ordinal": 1,
        "field": {
          "Aggregation": {
            "Expression": {
              "Column": {
                "Expression": {
                  "SourceRef": {
                    "Entity": "main"
                  }
                },
                "Property": "input_majo.Responsabilidad"
              }
            },
            "Function": 5
          }
        },
        "type": "Advanced"
      },
      {
        "name": "756cd7c334d19a91010c",
        "ordinal": 2,
        "field": {
          "Aggregation": {
            "Expression": {
              "Column": {
                "Expression": {
                  "SourceRef": {
                    "Entity": "main"
                  }
                },
                "Property": "input_majo.output.Contactados"
              }
            },
            "Function": 5
          }
        },
        "type": "Advanced",
        "howCreated": "User"
      },
      {
        "name": "a695caea04464ed60b80",
        "ordinal": 3,
        "field": {
          "Column": {
            "Expression": {
              "SourceRef": {
                "Entity": "DimCalendario"
              }
            },
            "Property": "Dia"
          }
        },
        "type": "Advanced"
      },
      {
        "name": "bb9a43d58eb8a9adcb1d",
        "ordinal": 4,
        "field": {
          "Column": {
            "Expression": {
              "SourceRef": {
                "Entity": "main"
              }
            },
            "Property": "input_majo.Responsabilidad"
          }
        },
        "type": "Categorical",
        "filter": {
          "Version": 2,
          "From": [
            {
              "Name": "m",
              "Entity": "main",
              "Type": 0
            }
          ],
          "Where": [
            {
              "Condition": {
                "In": {
                  "Expressions": [
                    {
                      "Column": {
                        "Expression": {
                          "SourceRef": {
                            "Source": "m"
                          }
                        },
                        "Property": "input_majo.Responsabilidad"
                      }
                    }
                  ],
                  "Values": [
                    [
                      {
                        "Literal": {
                          "Value": "'Responsabilidad del Cliente'"
                        }
                      }
                    ]
                  ]
                }
              }
            }
          ]
        },
        "howCreated": "User"
      }
    ],
    "filterSortOrder": "Custom"
  }
}