{
  "$schema": "https://developer.microsoft.com/json-schemas/fabric/item/report/definition/visualContainer/2.6.0/schema.json",
  "name": "c5d6e7f8a9b0c1d2e3f4",
  "position": {
    "x": 830,
    "y": 10,
    "z": 2000,
    "height": 110,
    "width": 440,
    "tabOrder": 2000
  },
  "visual": {
    "visualType": "cardVisual",
    "query": {
      "queryState": {
        "Data": {
          "projections": [
            {
              "field": {
                "Measure": {
                  "Expression": {
                    "SourceRef": {
                      "Entity": "01_Medidas"
                    }
                  },
                  "Property": "% Carga al 0800"
                }
              },
              "queryRef": "01_Medidas.% Carga al 0800",
              "nativeQueryRef": "% Carga al 0800"
            }
          ]
        }
      },
      "sortDefinition": {
        "sort": [
          {
            "field": {
              "Measure": {
                "Expression": {
                  "SourceRef": {
                    "Entity": "01_Medidas"
                  }
                },
                "Property": "% Carga al 0800"
              }
            },
            "direction": "Descending"
          }
        ],
        "isDefaultSort": true
      }
    },
    "drillFilterOtherVisuals": true
  }
}