{
  "$schema": "https://developer.microsoft.com/json-schemas/fabric/item/report/definition/visualContainer/2.6.0/schema.json",
  "name": "536b9686e02a1e4697e0",
  "position": {
    "x": 11.818181818181817,
    "y": 921.81818181818176,
    "z": 1000,
    "height": 28.18181818181818,
    "width": 1253.6363636363635,
    "tabOrder": 1000
  },
  "visual": {
    "visualType": "textbox",
    "objects": {
      "general": [
        {
          "properties": {
            "paragraphs": [
              {
                "textRuns": [
                  {
                    "value": "ANÁLISIS TEMPORAL Y TENDENCIAS",
                    "textStyle": {
                      "fontWeight": "bold",
                      "fontFamily": "Segoe UI Semibold",
                      "fontSize": "13px",
                      "color": "#0f172a"
                    }
                  }
                ]
              }
            ]
          }
        }
      ]
    },
    "drillFilterOtherVisuals": true
  }
}